Metadata-Version: 2.1
Name: pywebkit
Version: 0.2.0
Summary: A Library for Web Development with ease
Home-page: https://github.com/Yaseen549/pywebkit
Author: MOHAMED YASEEN SHERIFF S
Author-email: fantasticyaseenshariff@gmail.com
License: MIT
Download-URL: https://github.com/Yaseen549/pywebkit/archive/refs/tags/v0.2.0.tar.gz
Keywords: PY,WEB,KIT,PYWEBKIT
Platform: UNKNOWN
Classifier: Development Status :: 3 - Alpha
Classifier: Intended Audience :: Developers
Classifier: Topic :: Software Development :: Build Tools
Classifier: License :: OSI Approved :: MIT License
Classifier: Programming Language :: Python :: 3
Classifier: Programming Language :: Python :: 3.4
Classifier: Programming Language :: Python :: 3.5
Classifier: Programming Language :: Python :: 3.6
